README.rst
octave.py
setup.py
sage_octave.egg-info/PKG-INFO
sage_octave.egg-info/SOURCES.txt
sage_octave.egg-info/dependency_links.txt
sage_octave.egg-info/not-zip-safe
sage_octave.egg-info/top_level.txt