Metadata-Version: 1.1
Name: sage-octave
Version: 0.1.4
Summary: Improved version of the octave interface for Sage
Home-page: http://github.com/billpage/sage-octave
Author: Bill Page
Author-email: bill.page@newsynthesis.org
License: GPL
Keywords: sagemath interface octave
Platform: UNKNOWN
Classifier: Development Status :: 3 - Alpha
Classifier: Environment :: Console
Classifier: Environment :: Web Environment
Classifier: Intended Audience :: Developers
Classifier: Intended Audience :: End Users/Desktop
Classifier: Intended Audience :: Science/Research
Classifier: Topic :: Scientific/Engineering :: Mathematics
Classifier: Topic :: Scientific/Engineering :: Interface Engine/Protocol Translator
Classifier: License :: OSI Approved :: GNU General Public License v2 or later (GPLv2+)
Classifier: Programming Language :: Python :: 2
Classifier: Programming Language :: Python :: 2.6
Classifier: Programming Language :: Python :: 2.7
